netsblox/__init__.py
netsblox/__main__.py
netsblox/app.py
netsblox/colors.py
netsblox/common.py
netsblox/concurrency.py
netsblox/dev.py
netsblox/editor.py
netsblox/events.py
netsblox/generics.py
netsblox/graphical.py
netsblox/rooms.py
netsblox/snap.py
netsblox/sound.py
netsblox/transform.py
netsblox/assets/default-blocks.json
netsblox/assets/default-imports.json
netsblox/assets/default-project.json
netsblox/assets/examples/covid-19-daily.json
netsblox/assets/examples/street-view.json
netsblox/assets/examples/weather-app.json
netsblox/assets/fonts/Droid/DroidSansFallback.ttf
netsblox/assets/fonts/Droid/README.md
netsblox/assets/img/blocks/control/broadcast.png
netsblox/assets/img/blocks/control/clone-expr.png
netsblox/assets/img/blocks/control/clone-stmt.png
netsblox/assets/img/blocks/control/if-else-expr.png
netsblox/assets/img/blocks/control/if-else.png
netsblox/assets/img/blocks/control/if.png
netsblox/assets/img/blocks/control/loop-for.png
netsblox/assets/img/blocks/control/loop-forever.png
netsblox/assets/img/blocks/control/loop-repeat.png
netsblox/assets/img/blocks/control/loop-until.png
netsblox/assets/img/blocks/control/no-yield.png
netsblox/assets/img/blocks/control/onkey.png
netsblox/assets/img/blocks/control/onmouse-scroll-up.png
netsblox/assets/img/blocks/control/onmouse-up.png
netsblox/assets/img/blocks/control/onstart-clone.png
netsblox/assets/img/blocks/control/onstart.png
netsblox/assets/img/blocks/control/receive.png
netsblox/assets/img/blocks/control/return.png
netsblox/assets/img/blocks/control/sleep.png
netsblox/assets/img/blocks/control/throw.png
netsblox/assets/img/blocks/control/try.png
netsblox/assets/img/blocks/looks/change-scale.png
netsblox/assets/img/blocks/looks/get-costume-num.png
netsblox/assets/img/blocks/looks/get-scale.png
netsblox/assets/img/blocks/looks/get-visible.png
netsblox/assets/img/blocks/looks/say-duration.png
netsblox/assets/img/blocks/looks/say.png
netsblox/assets/img/blocks/looks/set-costume.png
netsblox-0.6.20.dist-info/LICENSE
netsblox-0.6.20.dist-info/METADATA
netsblox-0.6.20.dist-info/WHEEL
netsblox-0.6.20.dist-info/top_level.txt
netsblox-0.6.20.dist-info/RECORD
