Metadata-Version: 2.1
Name: netsblox
Version: 0.6.20
Summary: A python interface for accessing NetsBlox services
Home-page: https://github.com/dragazo/NetsBlox-python
Author: Devin Jean
Author-email: devin.c.jean@vanderbilt.edu
License: Apache 2.0
Platform: UNKNOWN
Classifier: Development Status :: 1 - Planning
Classifier: License :: OSI Approved :: Apache Software License
Classifier: Programming Language :: Python :: 3
Classifier: Intended Audience :: Education
Classifier: Topic :: Education
Classifier: Topic :: Internet
License-File: LICENSE
Requires-Dist: darkdetect
Requires-Dist: deprecation
Requires-Dist: gelidum
Requires-Dist: jedi
Requires-Dist: nb2pb (>=0.1.15)
Requires-Dist: numpy
Requires-Dist: parso
Requires-Dist: pillow (>=8.2)
Requires-Dist: pygame
Requires-Dist: randomname
Requires-Dist: requests
Requires-Dist: websocket-client
